yeom/__init__.py
yeom/doe.py
yeom-0.1.0.dist-info/METADATA
yeom-0.1.0.dist-info/WHEEL
yeom-0.1.0.dist-info/licenses/LICENSE
yeom-0.1.0.dist-info/RECORD
