Metadata-Version: 2.4
Name: yeom
Version: 0.1.0
Summary: Simple statistics and machine learning utilities
Author: YU Jaemyoung
License: Copyright 2025 YU Jaemyoung
License-File: LICENSE
Keywords: design-of-experiments,machine-learning,statistics,utils
Classifier: Development Status :: 3 - Alpha
Classifier: Intended Audience :: Science/Research
Classifier: License :: OSI Approved :: MIT License
Classifier: Programming Language :: Python
Classifier: Programming Language :: Python :: 3
Classifier: Programming Language :: Python :: 3 :: Only
Classifier: Programming Language :: Python :: 3.9
Classifier: Programming Language :: Python :: 3.10
Classifier: Programming Language :: Python :: 3.11
Classifier: Programming Language :: Python :: 3.12
Classifier: Topic :: Scientific/Engineering
Requires-Python: >=3.9
Requires-Dist: numpy>=1.22
Requires-Dist: pandas>=1.4
Requires-Dist: patsy>=0.5
Requires-Dist: scipy>=1.8
Requires-Dist: statsmodels>=0.13
